{
    "metadata": {
        "timestamp": "2026-01-05T19:32:13.623143",
        "type": "programs",
        "yearRange": "All-Time",
        "totalItems": 93,
        "description": "Top programs for state: (UT)"
    },
    "topItem": {
        "rank": 1,
        "program": "Highland Lone Peak (UT)",
        "combined": 46.415,
        "margin": 42.958,
        "win_loss": 3.326,
        "offense": 16.482,
        "defense": 1.043,
        "state": "UT",
        "mascot": "Knights",
        "backgroundColor": "#800000",
        "textColor": "#FFFFFF",
        "logoURL": "/static-football-rankings/images/logos/38921_LonePeak_Mascot.jpg",
        "schoolLogoURL": "/static-football-rankings/images/school_logos/38921_LonePeak_School.png",
        "website": "https://lphs.alpineschools.org/",
        "seasons": 28,
        "hasProgramPage": false,
        "programPageUrl": ""
    },
    "items": [
        {
            "rank": 1,
            "program": "Highland Lone Peak (UT)",
            "combined": 46.415,
            "margin": 42.958,
            "win_loss": 3.326,
            "offense": 16.482,
            "defense": 1.043,
            "state": "UT",
            "mascot": "Knights",
            "backgroundColor": "#800000",
            "textColor": "#FFFFFF",
            "logoURL": "/static-football-rankings/images/logos/38921_LonePeak_Mascot.jpg",
            "schoolLogoURL": "/static-football-rankings/images/school_logos/38921_LonePeak_School.png",
            "website": "https://lphs.alpineschools.org/",
            "seasons": 28,
            "hasProgramPage": false,
            "programPageUrl": ""
        },
        {
            "rank": 2,
            "program": "Provo Timpview (UT)",
            "combined": 33.134,
            "margin": 32.459,
            "win_loss": 0.626,
            "offense": 17.946,
            "defense": 8.001,
            "state": "UT",
            "mascot": "",
            "backgroundColor": "#333333",
            "textColor": "#FFFFFF",
            "logoURL": "",
            "schoolLogoURL": "",
            "website": "",
            "seasons": 48,
            "hasProgramPage": false,
            "programPageUrl": ""
        },
        {
            "rank": 3,
            "program": "Plain City Fremont (UT)",
            "combined": 31.695,
            "margin": 29.979,
            "win_loss": 1.71,
            "offense": 14.294,
            "defense": 6.486,
            "state": "UT",
            "mascot": "",
            "backgroundColor": "#333333",
            "textColor": "#FFFFFF",
            "logoURL": "",
            "schoolLogoURL": "",
            "website": "",
            "seasons": 31,
            "hasProgramPage": false,
            "programPageUrl": ""
        },
        {
            "rank": 4,
            "program": "Sandy Alta (UT)",
            "combined": 31.051,
            "margin": 30.596,
            "win_loss": 0.428,
            "offense": 17.377,
            "defense": 7.922,
            "state": "UT",
            "mascot": "",
            "backgroundColor": "#333333",
            "textColor": "#FFFFFF",
            "logoURL": "",
            "schoolLogoURL": "",
            "website": "",
            "seasons": 47,
            "hasProgramPage": false,
            "programPageUrl": ""
        },
        {
            "rank": 5,
            "program": "Riverton (UT)",
            "combined": 28.67,
            "margin": 26.988,
            "win_loss": 1.751,
            "offense": 16.624,
            "defense": 3.572,
            "state": "UT",
            "mascot": "",
            "backgroundColor": "#333333",
            "textColor": "#FFFFFF",
            "logoURL": "",
            "schoolLogoURL": "",
            "website": "",
            "seasons": 26,
            "hasProgramPage": false,
            "programPageUrl": ""
        },
        {
            "rank": 6,
            "program": "West Valley City Hunter (UT)",
            "combined": 26.632,
            "margin": 25.828,
            "win_loss": 0.825,
            "offense": 12.875,
            "defense": 8.307,
            "state": "UT",
            "mascot": "",
            "backgroundColor": "#333333",
            "textColor": "#FFFFFF",
            "logoURL": "",
            "schoolLogoURL": "",
            "website": "",
            "seasons": 35,
            "hasProgramPage": false,
            "programPageUrl": ""
        },
        {
            "rank": 7,
            "program": "Layton Northridge (UT)",
            "combined": 26.031,
            "margin": 25.147,
            "win_loss": 0.896,
            "offense": 15.957,
            "defense": 7.178,
            "state": "UT",
            "mascot": "",
            "backgroundColor": "#333333",
            "textColor": "#FFFFFF",
            "logoURL": "",
            "schoolLogoURL": "",
            "website": "",
            "seasons": 33,
            "hasProgramPage": false,
            "programPageUrl": ""
        },
        {
            "rank": 8,
            "program": "Salt Lake City Brighton (UT)",
            "combined": 25.912,
            "margin": 25.933,
            "win_loss": -0.078,
            "offense": 14.058,
            "defense": 8.756,
            "state": "UT",
            "mascot": "",
            "backgroundColor": "#333333",
            "textColor": "#FFFFFF",
            "logoURL": "",
            "schoolLogoURL": "",
            "website": "",
            "seasons": 56,
            "hasProgramPage": false,
            "programPageUrl": ""
        },
        {
            "rank": 9,
            "program": "Salt Lake City Skyline (UT)",
            "combined": 23.564,
            "margin": 23.632,
            "win_loss": -0.072,
            "offense": 14.23,
            "defense": 12.995,
            "state": "UT",
            "mascot": "",
            "backgroundColor": "#333333",
            "textColor": "#FFFFFF",
            "logoURL": "",
            "schoolLogoURL": "",
            "website": "",
            "seasons": 63,
            "hasProgramPage": false,
            "programPageUrl": ""
        },
        {
            "rank": 10,
            "program": "Hyrum Mountain Crest (UT)",
            "combined": 23.333,
            "margin": 23.385,
            "win_loss": -0.073,
            "offense": 14.262,
            "defense": 8.307,
            "state": "UT",
            "mascot": "",
            "backgroundColor": "#333333",
            "textColor": "#FFFFFF",
            "logoURL": "",
            "schoolLogoURL": "",
            "website": "",
            "seasons": 42,
            "hasProgramPage": false,
            "programPageUrl": ""
        },
        {
            "rank": 11,
            "program": "Salt Lake City East (UT)",
            "combined": 22.586,
            "margin": 21.864,
            "win_loss": 0.707,
            "offense": 11.292,
            "defense": 9.795,
            "state": "UT",
            "mascot": "",
            "backgroundColor": "#333333",
            "textColor": "#FFFFFF",
            "logoURL": "",
            "schoolLogoURL": "",
            "website": "",
            "seasons": 101,
            "hasProgramPage": false,
            "programPageUrl": ""
        },
        {
            "rank": 12,
            "program": "Salt Lake City Highland (UT)",
            "combined": 20.264,
            "margin": 20.604,
            "win_loss": -0.35,
            "offense": 13.632,
            "defense": 11.081,
            "state": "UT",
            "mascot": "",
            "backgroundColor": "#333333",
            "textColor": "#FFFFFF",
            "logoURL": "",
            "schoolLogoURL": "",
            "website": "",
            "seasons": 68,
            "hasProgramPage": false,
            "programPageUrl": ""
        },
        {
            "rank": 13,
            "program": "South Jordan Bingham (UT)",
            "combined": 19.615,
            "margin": 19.897,
            "win_loss": -0.299,
            "offense": 15.627,
            "defense": 6.84,
            "state": "UT",
            "mascot": "",
            "backgroundColor": "#333333",
            "textColor": "#FFFFFF",
            "logoURL": "",
            "schoolLogoURL": "",
            "website": "",
            "seasons": 71,
            "hasProgramPage": false,
            "programPageUrl": ""
        },
        {
            "rank": 14,
            "program": "Saint George Snow Canyon (UT)",
            "combined": 19.077,
            "margin": 18.747,
            "win_loss": 0.286,
            "offense": 14.132,
            "defense": 7.523,
            "state": "UT",
            "mascot": "",
            "backgroundColor": "#333333",
            "textColor": "#FFFFFF",
            "logoURL": "",
            "schoolLogoURL": "",
            "website": "",
            "seasons": 31,
            "hasProgramPage": false,
            "programPageUrl": ""
        },
        {
            "rank": 15,
            "program": "Orem (UT)",
            "combined": 18.688,
            "margin": 19.248,
            "win_loss": -0.591,
            "offense": 14.517,
            "defense": 9.717,
            "state": "UT",
            "mascot": "",
            "backgroundColor": "#333333",
            "textColor": "#FFFFFF",
            "logoURL": "",
            "schoolLogoURL": "",
            "website": "",
            "seasons": 67,
            "hasProgramPage": false,
            "programPageUrl": ""
        },
        {
            "rank": 16,
            "program": "American Fork (UT)",
            "combined": 18.035,
            "margin": 17.978,
            "win_loss": 0.041,
            "offense": 16.097,
            "defense": 8.428,
            "state": "UT",
            "mascot": "",
            "backgroundColor": "#333333",
            "textColor": "#FFFFFF",
            "logoURL": "",
            "schoolLogoURL": "",
            "website": "",
            "seasons": 83,
            "hasProgramPage": false,
            "programPageUrl": ""
        },
        {
            "rank": 17,
            "program": "Kaysville Davis (UT)",
            "combined": 17.864,
            "margin": 17.608,
            "win_loss": 0.218,
            "offense": 11.155,
            "defense": 11.271,
            "state": "UT",
            "mascot": "",
            "backgroundColor": "#333333",
            "textColor": "#FFFFFF",
            "logoURL": "",
            "schoolLogoURL": "",
            "website": "",
            "seasons": 90,
            "hasProgramPage": false,
            "programPageUrl": ""
        },
        {
            "rank": 18,
            "program": "Draper Juan Diego Catholic (UT)",
            "combined": 17.434,
            "margin": 16.755,
            "win_loss": 0.696,
            "offense": 13.963,
            "defense": 7.314,
            "state": "UT",
            "mascot": "",
            "backgroundColor": "#333333",
            "textColor": "#FFFFFF",
            "logoURL": "",
            "schoolLogoURL": "",
            "website": "",
            "seasons": 25,
            "hasProgramPage": false,
            "programPageUrl": ""
        },
        {
            "rank": 19,
            "program": "Salt Lake City Olympus (UT)",
            "combined": 17.081,
            "margin": 17.637,
            "win_loss": -0.556,
            "offense": 12.986,
            "defense": 9.488,
            "state": "UT",
            "mascot": "",
            "backgroundColor": "#333333",
            "textColor": "#FFFFFF",
            "logoURL": "",
            "schoolLogoURL": "",
            "website": "",
            "seasons": 72,
            "hasProgramPage": false,
            "programPageUrl": ""
        },
        {
            "rank": 20,
            "program": "Layton (UT)",
            "combined": 16.941,
            "margin": 17.946,
            "win_loss": -1.012,
            "offense": 15.065,
            "defense": 8.852,
            "state": "UT",
            "mascot": "",
            "backgroundColor": "#333333",
            "textColor": "#FFFFFF",
            "logoURL": "",
            "schoolLogoURL": "",
            "website": "",
            "seasons": 57,
            "hasProgramPage": false,
            "programPageUrl": ""
        },
        {
            "rank": 21,
            "program": "Bountiful (UT)",
            "combined": 16.7,
            "margin": 17.351,
            "win_loss": -0.677,
            "offense": 12.632,
            "defense": 10.102,
            "state": "UT",
            "mascot": "",
            "backgroundColor": "#333333",
            "textColor": "#FFFFFF",
            "logoURL": "",
            "schoolLogoURL": "",
            "website": "",
            "seasons": 70,
            "hasProgramPage": false,
            "programPageUrl": ""
        },
        {
            "rank": 22,
            "program": "West Jordan (UT)",
            "combined": 16.003,
            "margin": 16.925,
            "win_loss": -0.894,
            "offense": 15.615,
            "defense": 8.926,
            "state": "UT",
            "mascot": "",
            "backgroundColor": "#333333",
            "textColor": "#FFFFFF",
            "logoURL": "",
            "schoolLogoURL": "",
            "website": "",
            "seasons": 44,
            "hasProgramPage": false,
            "programPageUrl": ""
        },
        {
            "rank": 23,
            "program": "Salt Lake City West (UT)",
            "combined": 15.076,
            "margin": 15.099,
            "win_loss": -0.031,
            "offense": 11.218,
            "defense": 9.578,
            "state": "UT",
            "mascot": "",
            "backgroundColor": "#333333",
            "textColor": "#FFFFFF",
            "logoURL": "",
            "schoolLogoURL": "",
            "website": "",
            "seasons": 99,
            "hasProgramPage": false,
            "programPageUrl": ""
        },
        {
            "rank": 24,
            "program": "Saint George Pine View (UT)",
            "combined": 14.91,
            "margin": 15.922,
            "win_loss": -1.016,
            "offense": 16.595,
            "defense": 8.134,
            "state": "UT",
            "mascot": "",
            "backgroundColor": "#333333",
            "textColor": "#FFFFFF",
            "logoURL": "",
            "schoolLogoURL": "",
            "website": "",
            "seasons": 42,
            "hasProgramPage": false,
            "programPageUrl": ""
        },
        {
            "rank": 25,
            "program": "Smithfield Sky View (UT)",
            "combined": 14.598,
            "margin": 15.812,
            "win_loss": -1.228,
            "offense": 18.294,
            "defense": 7.138,
            "state": "UT",
            "mascot": "",
            "backgroundColor": "#333333",
            "textColor": "#FFFFFF",
            "logoURL": "",
            "schoolLogoURL": "",
            "website": "",
            "seasons": 61,
            "hasProgramPage": false,
            "programPageUrl": ""
        },
        {
            "rank": 26,
            "program": "Washington Terrace Bonneville (UT)",
            "combined": 14.219,
            "margin": 15.295,
            "win_loss": -1.102,
            "offense": 13.61,
            "defense": 10.225,
            "state": "UT",
            "mascot": "",
            "backgroundColor": "#333333",
            "textColor": "#FFFFFF",
            "logoURL": "",
            "schoolLogoURL": "",
            "website": "",
            "seasons": 65,
            "hasProgramPage": false,
            "programPageUrl": ""
        },
        {
            "rank": 27,
            "program": "Brigham City Box Elder (UT)",
            "combined": 12.838,
            "margin": 13.515,
            "win_loss": -0.702,
            "offense": 13.61,
            "defense": 8.881,
            "state": "UT",
            "mascot": "",
            "backgroundColor": "#333333",
            "textColor": "#FFFFFF",
            "logoURL": "",
            "schoolLogoURL": "",
            "website": "",
            "seasons": 80,
            "hasProgramPage": false,
            "programPageUrl": ""
        },
        {
            "rank": 28,
            "program": "Bountiful Viewmont (UT)",
            "combined": 12.661,
            "margin": 13.998,
            "win_loss": -1.297,
            "offense": 15.121,
            "defense": 9.421,
            "state": "UT",
            "mascot": "",
            "backgroundColor": "#333333",
            "textColor": "#FFFFFF",
            "logoURL": "",
            "schoolLogoURL": "",
            "website": "",
            "seasons": 61,
            "hasProgramPage": false,
            "programPageUrl": ""
        },
        {
            "rank": 29,
            "program": "Sandy Jordan (UT)",
            "combined": 12.33,
            "margin": 12.478,
            "win_loss": -0.14,
            "offense": 11.065,
            "defense": 10.979,
            "state": "UT",
            "mascot": "",
            "backgroundColor": "#333333",
            "textColor": "#FFFFFF",
            "logoURL": "",
            "schoolLogoURL": "",
            "website": "",
            "seasons": 96,
            "hasProgramPage": false,
            "programPageUrl": ""
        },
        {
            "rank": 30,
            "program": "Woods Cross (UT)",
            "combined": 12.295,
            "margin": 13.831,
            "win_loss": -1.492,
            "offense": 14.985,
            "defense": 8.452,
            "state": "UT",
            "mascot": "",
            "backgroundColor": "#333333",
            "textColor": "#FFFFFF",
            "logoURL": "",
            "schoolLogoURL": "",
            "website": "",
            "seasons": 49,
            "hasProgramPage": false,
            "programPageUrl": ""
        },
        {
            "rank": 31,
            "program": "Orem Timpanogos (UT)",
            "combined": 11.988,
            "margin": 12.005,
            "win_loss": -0.002,
            "offense": 12.495,
            "defense": 9.542,
            "state": "UT",
            "mascot": "",
            "backgroundColor": "#333333",
            "textColor": "#FFFFFF",
            "logoURL": "",
            "schoolLogoURL": "",
            "website": "",
            "seasons": 29,
            "hasProgramPage": false,
            "programPageUrl": ""
        },
        {
            "rank": 32,
            "program": "Roy (UT)",
            "combined": 11.309,
            "margin": 12.732,
            "win_loss": -1.44,
            "offense": 15.226,
            "defense": 9.933,
            "state": "UT",
            "mascot": "",
            "backgroundColor": "#333333",
            "textColor": "#FFFFFF",
            "logoURL": "",
            "schoolLogoURL": "",
            "website": "",
            "seasons": 60,
            "hasProgramPage": false,
            "programPageUrl": ""
        },
        {
            "rank": 33,
            "program": "Orem Mountain View (UT)",
            "combined": 10.391,
            "margin": 11.84,
            "win_loss": -1.406,
            "offense": 12.27,
            "defense": 10.882,
            "state": "UT",
            "mascot": "",
            "backgroundColor": "#333333",
            "textColor": "#FFFFFF",
            "logoURL": "",
            "schoolLogoURL": "",
            "website": "",
            "seasons": 45,
            "hasProgramPage": false,
            "programPageUrl": ""
        },
        {
            "rank": 34,
            "program": "Clearfield (UT)",
            "combined": 9.478,
            "margin": 11.115,
            "win_loss": -1.591,
            "offense": 13.5,
            "defense": 9.839,
            "state": "UT",
            "mascot": "",
            "backgroundColor": "#333333",
            "textColor": "#FFFFFF",
            "logoURL": "",
            "schoolLogoURL": "",
            "website": "",
            "seasons": 63,
            "hasProgramPage": false,
            "programPageUrl": ""
        },
        {
            "rank": 35,
            "program": "Logan (UT)",
            "combined": 9.324,
            "margin": 10.239,
            "win_loss": -0.919,
            "offense": 15.192,
            "defense": 6.75,
            "state": "UT",
            "mascot": "",
            "backgroundColor": "#333333",
            "textColor": "#FFFFFF",
            "logoURL": "",
            "schoolLogoURL": "",
            "website": "",
            "seasons": 86,
            "hasProgramPage": false,
            "programPageUrl": ""
        },
        {
            "rank": 36,
            "program": "Springville (UT)",
            "combined": 8.044,
            "margin": 9.142,
            "win_loss": -1.119,
            "offense": 15.291,
            "defense": 9.353,
            "state": "UT",
            "mascot": "",
            "backgroundColor": "#333333",
            "textColor": "#FFFFFF",
            "logoURL": "",
            "schoolLogoURL": "",
            "website": "",
            "seasons": 78,
            "hasProgramPage": false,
            "programPageUrl": ""
        },
        {
            "rank": 37,
            "program": "Provo (UT)",
            "combined": 8.005,
            "margin": 8.921,
            "win_loss": -0.893,
            "offense": 11.992,
            "defense": 10.607,
            "state": "UT",
            "mascot": "",
            "backgroundColor": "#333333",
            "textColor": "#FFFFFF",
            "logoURL": "",
            "schoolLogoURL": "",
            "website": "",
            "seasons": 87,
            "hasProgramPage": false,
            "programPageUrl": ""
        },
        {
            "rank": 38,
            "program": "Pleasant Grove (UT)",
            "combined": 7.05,
            "margin": 8.14,
            "win_loss": -1.106,
            "offense": 16.687,
            "defense": 6.187,
            "state": "UT",
            "mascot": "",
            "backgroundColor": "#333333",
            "textColor": "#FFFFFF",
            "logoURL": "",
            "schoolLogoURL": "",
            "website": "",
            "seasons": 82,
            "hasProgramPage": false,
            "programPageUrl": ""
        },
        {
            "rank": 39,
            "program": "Saint George Dixie (UT)",
            "combined": 6.532,
            "margin": 8.39,
            "win_loss": -1.869,
            "offense": 15.759,
            "defense": 8.052,
            "state": "UT",
            "mascot": "",
            "backgroundColor": "#333333",
            "textColor": "#FFFFFF",
            "logoURL": "",
            "schoolLogoURL": "",
            "website": "",
            "seasons": 62,
            "hasProgramPage": false,
            "programPageUrl": ""
        },
        {
            "rank": 40,
            "program": "West Valley City Granger (UT)",
            "combined": 6.076,
            "margin": 8.044,
            "win_loss": -1.997,
            "offense": 14.438,
            "defense": 10.102,
            "state": "UT",
            "mascot": "",
            "backgroundColor": "#333333",
            "textColor": "#FFFFFF",
            "logoURL": "",
            "schoolLogoURL": "",
            "website": "",
            "seasons": 63,
            "hasProgramPage": false,
            "programPageUrl": ""
        },
        {
            "rank": 41,
            "program": "Pleasant View Weber (UT)",
            "combined": 5.121,
            "margin": 6.718,
            "win_loss": -1.599,
            "offense": 14.991,
            "defense": 6.59,
            "state": "UT",
            "mascot": "",
            "backgroundColor": "#333333",
            "textColor": "#FFFFFF",
            "logoURL": "",
            "schoolLogoURL": "",
            "website": "",
            "seasons": 83,
            "hasProgramPage": false,
            "programPageUrl": ""
        },
        {
            "rank": 42,
            "program": "West Jordan Copper Hills (UT)",
            "combined": 4.558,
            "margin": 5.366,
            "win_loss": -0.808,
            "offense": 10.481,
            "defense": 10.292,
            "state": "UT",
            "mascot": "",
            "backgroundColor": "#333333",
            "textColor": "#FFFFFF",
            "logoURL": "",
            "schoolLogoURL": "",
            "website": "",
            "seasons": 30,
            "hasProgramPage": false,
            "programPageUrl": ""
        },
        {
            "rank": 43,
            "program": "Salt Lake City Cottonwood (UT)",
            "combined": 4.508,
            "margin": 6.643,
            "win_loss": -2.118,
            "offense": 15.018,
            "defense": 10.129,
            "state": "UT",
            "mascot": "",
            "backgroundColor": "#333333",
            "textColor": "#FFFFFF",
            "logoURL": "",
            "schoolLogoURL": "",
            "website": "",
            "seasons": 55,
            "hasProgramPage": false,
            "programPageUrl": ""
        },
        {
            "rank": 44,
            "program": "Kearns (UT)",
            "combined": 4.486,
            "margin": 6.575,
            "win_loss": -2.083,
            "offense": 15.731,
            "defense": 10.609,
            "state": "UT",
            "mascot": "",
            "backgroundColor": "#333333",
            "textColor": "#FFFFFF",
            "logoURL": "",
            "schoolLogoURL": "",
            "website": "",
            "seasons": 57,
            "hasProgramPage": false,
            "programPageUrl": ""
        },
        {
            "rank": 45,
            "program": "Lehi (UT)",
            "combined": 3.816,
            "margin": 5.375,
            "win_loss": -1.568,
            "offense": 16.556,
            "defense": 5.697,
            "state": "UT",
            "mascot": "",
            "backgroundColor": "#333333",
            "textColor": "#FFFFFF",
            "logoURL": "",
            "schoolLogoURL": "",
            "website": "",
            "seasons": 83,
            "hasProgramPage": false,
            "programPageUrl": ""
        },
        {
            "rank": 46,
            "program": "Cedar City (UT)",
            "combined": 3.75,
            "margin": 6.132,
            "win_loss": -2.342,
            "offense": 15.6,
            "defense": 8.275,
            "state": "UT",
            "mascot": "",
            "backgroundColor": "#333333",
            "textColor": "#FFFFFF",
            "logoURL": "",
            "schoolLogoURL": "",
            "website": "",
            "seasons": 58,
            "hasProgramPage": false,
            "programPageUrl": ""
        },
        {
            "rank": 47,
            "program": "Spanish Fork (UT)",
            "combined": 3.704,
            "margin": 5.277,
            "win_loss": -1.59,
            "offense": 15.581,
            "defense": 7.399,
            "state": "UT",
            "mascot": "",
            "backgroundColor": "#333333",
            "textColor": "#FFFFFF",
            "logoURL": "",
            "schoolLogoURL": "",
            "website": "",
            "seasons": 82,
            "hasProgramPage": false,
            "programPageUrl": ""
        },
        {
            "rank": 48,
            "program": "Taylorsville (UT)",
            "combined": 2.683,
            "margin": 4.781,
            "win_loss": -2.094,
            "offense": 11.662,
            "defense": 11.364,
            "state": "UT",
            "mascot": "",
            "backgroundColor": "#333333",
            "textColor": "#FFFFFF",
            "logoURL": "",
            "schoolLogoURL": "",
            "website": "",
            "seasons": 44,
            "hasProgramPage": false,
            "programPageUrl": ""
        },
        {
            "rank": 49,
            "program": "Salt Lake City South (UT)",
            "combined": 2.02,
            "margin": 3.518,
            "win_loss": -1.473,
            "offense": 15.468,
            "defense": 6.696,
            "state": "UT",
            "mascot": "",
            "backgroundColor": "#333333",
            "textColor": "#FFFFFF",
            "logoURL": "",
            "schoolLogoURL": "",
            "website": "",
            "seasons": 51,
            "hasProgramPage": false,
            "programPageUrl": ""
        },
        {
            "rank": 50,
            "program": "Heber City Wasatch County (UT)",
            "combined": 1.138,
            "margin": 3.596,
            "win_loss": -2.418,
            "offense": 16.273,
            "defense": 7.067,
            "state": "UT",
            "mascot": "",
            "backgroundColor": "#333333",
            "textColor": "#FFFFFF",
            "logoURL": "",
            "schoolLogoURL": "",
            "website": "",
            "seasons": 61,
            "hasProgramPage": false,
            "programPageUrl": ""
        },
        {
            "rank": 51,
            "program": "Midvale Hillcrest (UT)",
            "combined": 1.026,
            "margin": 3.417,
            "win_loss": -2.325,
            "offense": 12.762,
            "defense": 11.472,
            "state": "UT",
            "mascot": "",
            "backgroundColor": "#333333",
            "textColor": "#FFFFFF",
            "logoURL": "",
            "schoolLogoURL": "",
            "website": "",
            "seasons": 62,
            "hasProgramPage": false,
            "programPageUrl": ""
        },
        {
            "rank": 52,
            "program": "Garland Bear River (UT)",
            "combined": 0.647,
            "margin": 2.745,
            "win_loss": -2.091,
            "offense": 15.32,
            "defense": 8.94,
            "state": "UT",
            "mascot": "",
            "backgroundColor": "#333333",
            "textColor": "#FFFFFF",
            "logoURL": "",
            "schoolLogoURL": "",
            "website": "",
            "seasons": 78,
            "hasProgramPage": false,
            "programPageUrl": ""
        },
        {
            "rank": 53,
            "program": "Magna Cyprus (UT)",
            "combined": 0.452,
            "margin": 2.817,
            "win_loss": -2.335,
            "offense": 13.659,
            "defense": 9.367,
            "state": "UT",
            "mascot": "",
            "backgroundColor": "#333333",
            "textColor": "#FFFFFF",
            "logoURL": "",
            "schoolLogoURL": "",
            "website": "",
            "seasons": 67,
            "hasProgramPage": false,
            "programPageUrl": ""
        },
        {
            "rank": 54,
            "program": "Delta (UT)",
            "combined": 0.249,
            "margin": 2.751,
            "win_loss": -2.527,
            "offense": 13.704,
            "defense": 10.426,
            "state": "UT",
            "mascot": "",
            "backgroundColor": "#333333",
            "textColor": "#FFFFFF",
            "logoURL": "",
            "schoolLogoURL": "",
            "website": "",
            "seasons": 59,
            "hasProgramPage": false,
            "programPageUrl": ""
        },
        {
            "rank": 55,
            "program": "Murray (UT)",
            "combined": 0.13,
            "margin": 2.241,
            "win_loss": -2.095,
            "offense": 12.551,
            "defense": 9.217,
            "state": "UT",
            "mascot": "",
            "backgroundColor": "#333333",
            "textColor": "#FFFFFF",
            "logoURL": "",
            "schoolLogoURL": "",
            "website": "",
            "seasons": 73,
            "hasProgramPage": false,
            "programPageUrl": ""
        },
        {
            "rank": 56,
            "program": "Salt Lake City Granite (UT)",
            "combined": -0.835,
            "margin": 1.225,
            "win_loss": -2.054,
            "offense": 11.161,
            "defense": 10.35,
            "state": "UT",
            "mascot": "",
            "backgroundColor": "#333333",
            "textColor": "#FFFFFF",
            "logoURL": "",
            "schoolLogoURL": "",
            "website": "",
            "seasons": 71,
            "hasProgramPage": false,
            "programPageUrl": ""
        },
        {
            "rank": 57,
            "program": "Morgan (UT)",
            "combined": -1.197,
            "margin": 1.364,
            "win_loss": -2.613,
            "offense": 16.473,
            "defense": 7.318,
            "state": "UT",
            "mascot": "",
            "backgroundColor": "#333333",
            "textColor": "#FFFFFF",
            "logoURL": "",
            "schoolLogoURL": "",
            "website": "",
            "seasons": 68,
            "hasProgramPage": false,
            "programPageUrl": ""
        },
        {
            "rank": 58,
            "program": "Beaver (UT)",
            "combined": -2.477,
            "margin": 0.512,
            "win_loss": -3.018,
            "offense": 15.808,
            "defense": 10.512,
            "state": "UT",
            "mascot": "",
            "backgroundColor": "#333333",
            "textColor": "#FFFFFF",
            "logoURL": "",
            "schoolLogoURL": "",
            "website": "",
            "seasons": 58,
            "hasProgramPage": false,
            "programPageUrl": ""
        },
        {
            "rank": 59,
            "program": "Tooele (UT)",
            "combined": -2.54,
            "margin": 0.047,
            "win_loss": -2.553,
            "offense": 13.905,
            "defense": 8.589,
            "state": "UT",
            "mascot": "",
            "backgroundColor": "#333333",
            "textColor": "#FFFFFF",
            "logoURL": "",
            "schoolLogoURL": "",
            "website": "",
            "seasons": 70,
            "hasProgramPage": false,
            "programPageUrl": ""
        },
        {
            "rank": 60,
            "program": "Payson (UT)",
            "combined": -3.922,
            "margin": -1.486,
            "win_loss": -2.39,
            "offense": 13.176,
            "defense": 8.766,
            "state": "UT",
            "mascot": "",
            "backgroundColor": "#333333",
            "textColor": "#FFFFFF",
            "logoURL": "",
            "schoolLogoURL": "",
            "website": "",
            "seasons": 77,
            "hasProgramPage": false,
            "programPageUrl": ""
        },
        {
            "rank": 61,
            "program": "Ogden (UT)",
            "combined": -4.001,
            "margin": -1.955,
            "win_loss": -2.029,
            "offense": 10.983,
            "defense": 10.92,
            "state": "UT",
            "mascot": "",
            "backgroundColor": "#333333",
            "textColor": "#FFFFFF",
            "logoURL": "",
            "schoolLogoURL": "",
            "website": "",
            "seasons": 89,
            "hasProgramPage": false,
            "programPageUrl": ""
        },
        {
            "rank": 62,
            "program": "Salt Lake City Judge Memorial Catholic (UT)",
            "combined": -4.151,
            "margin": -1.387,
            "win_loss": -2.742,
            "offense": 12.98,
            "defense": 12.465,
            "state": "UT",
            "mascot": "",
            "backgroundColor": "#333333",
            "textColor": "#FFFFFF",
            "logoURL": "",
            "schoolLogoURL": "",
            "website": "",
            "seasons": 61,
            "hasProgramPage": false,
            "programPageUrl": ""
        },
        {
            "rank": 63,
            "program": "Fillmore Millard County (UT)",
            "combined": -4.419,
            "margin": -1.423,
            "win_loss": -3.063,
            "offense": 14.215,
            "defense": 10.314,
            "state": "UT",
            "mascot": "",
            "backgroundColor": "#333333",
            "textColor": "#FFFFFF",
            "logoURL": "",
            "schoolLogoURL": "",
            "website": "",
            "seasons": 59,
            "hasProgramPage": false,
            "programPageUrl": ""
        },
        {
            "rank": 64,
            "program": "Kamas South Summit (UT)",
            "combined": -6.649,
            "margin": -3.197,
            "win_loss": -3.479,
            "offense": 16.041,
            "defense": 7.116,
            "state": "UT",
            "mascot": "",
            "backgroundColor": "#333333",
            "textColor": "#FFFFFF",
            "logoURL": "",
            "schoolLogoURL": "",
            "website": "",
            "seasons": 56,
            "hasProgramPage": false,
            "programPageUrl": ""
        },
        {
            "rank": 65,
            "program": "Cedar City Canyon View (UT)",
            "combined": -7.009,
            "margin": -5.164,
            "win_loss": -1.73,
            "offense": 9.098,
            "defense": 10.673,
            "state": "UT",
            "mascot": "",
            "backgroundColor": "#333333",
            "textColor": "#FFFFFF",
            "logoURL": "",
            "schoolLogoURL": "",
            "website": "",
            "seasons": 28,
            "hasProgramPage": false,
            "programPageUrl": ""
        },
        {
            "rank": 66,
            "program": "Park City (UT)",
            "combined": -7.472,
            "margin": -4.449,
            "win_loss": -3.037,
            "offense": 15.688,
            "defense": 8.632,
            "state": "UT",
            "mascot": "",
            "backgroundColor": "#333333",
            "textColor": "#FFFFFF",
            "logoURL": "",
            "schoolLogoURL": "",
            "website": "",
            "seasons": 64,
            "hasProgramPage": false,
            "programPageUrl": ""
        },
        {
            "rank": 67,
            "program": "Grantsville (UT)",
            "combined": -7.915,
            "margin": -4.793,
            "win_loss": -3.11,
            "offense": 13.872,
            "defense": 8.703,
            "state": "UT",
            "mascot": "",
            "backgroundColor": "#333333",
            "textColor": "#FFFFFF",
            "logoURL": "",
            "schoolLogoURL": "",
            "website": "",
            "seasons": 64,
            "hasProgramPage": false,
            "programPageUrl": ""
        },
        {
            "rank": 68,
            "program": "Blanding San Juan County (UT)",
            "combined": -7.933,
            "margin": -4.532,
            "win_loss": -3.453,
            "offense": 16.361,
            "defense": 9.284,
            "state": "UT",
            "mascot": "",
            "backgroundColor": "#333333",
            "textColor": "#FFFFFF",
            "logoURL": "",
            "schoolLogoURL": "",
            "website": "",
            "seasons": 60,
            "hasProgramPage": false,
            "programPageUrl": ""
        },
        {
            "rank": 69,
            "program": "Hurricane (UT)",
            "combined": -8.535,
            "margin": -5.037,
            "win_loss": -3.487,
            "offense": 17.599,
            "defense": 9.886,
            "state": "UT",
            "mascot": "",
            "backgroundColor": "#333333",
            "textColor": "#FFFFFF",
            "logoURL": "",
            "schoolLogoURL": "",
            "website": "",
            "seasons": 58,
            "hasProgramPage": false,
            "programPageUrl": ""
        },
        {
            "rank": 70,
            "program": "Kanab (UT)",
            "combined": -8.97,
            "margin": -5.371,
            "win_loss": -3.654,
            "offense": 15.096,
            "defense": 10.198,
            "state": "UT",
            "mascot": "",
            "backgroundColor": "#333333",
            "textColor": "#FFFFFF",
            "logoURL": "",
            "schoolLogoURL": "",
            "website": "",
            "seasons": 56,
            "hasProgramPage": false,
            "programPageUrl": ""
        },
        {
            "rank": 71,
            "program": "Mount Pleasant North Sanpete (UT)",
            "combined": -11.304,
            "margin": -7.577,
            "win_loss": -3.683,
            "offense": 15.814,
            "defense": 6.686,
            "state": "UT",
            "mascot": "",
            "backgroundColor": "#333333",
            "textColor": "#FFFFFF",
            "logoURL": "",
            "schoolLogoURL": "",
            "website": "",
            "seasons": 63,
            "hasProgramPage": false,
            "programPageUrl": ""
        },
        {
            "rank": 72,
            "program": "Price Carbon County (UT)",
            "combined": -11.372,
            "margin": -8.638,
            "win_loss": -2.7,
            "offense": 10.341,
            "defense": 10.205,
            "state": "UT",
            "mascot": "",
            "backgroundColor": "#333333",
            "textColor": "#FFFFFF",
            "logoURL": "",
            "schoolLogoURL": "",
            "website": "",
            "seasons": 92,
            "hasProgramPage": false,
            "programPageUrl": ""
        },
        {
            "rank": 73,
            "program": "Richfield (UT)",
            "combined": -12.306,
            "margin": -8.531,
            "win_loss": -3.792,
            "offense": 14.264,
            "defense": 8.745,
            "state": "UT",
            "mascot": "",
            "backgroundColor": "#333333",
            "textColor": "#FFFFFF",
            "logoURL": "",
            "schoolLogoURL": "",
            "website": "",
            "seasons": 59,
            "hasProgramPage": false,
            "programPageUrl": ""
        },
        {
            "rank": 74,
            "program": "Ogden Ben Lomond (UT)",
            "combined": -12.437,
            "margin": -8.791,
            "win_loss": -3.596,
            "offense": 13.711,
            "defense": 10.427,
            "state": "UT",
            "mascot": "",
            "backgroundColor": "#333333",
            "textColor": "#FFFFFF",
            "logoURL": "",
            "schoolLogoURL": "",
            "website": "",
            "seasons": 69,
            "hasProgramPage": false,
            "programPageUrl": ""
        },
        {
            "rank": 75,
            "program": "Vernal Uintah County (UT)",
            "combined": -12.5,
            "margin": -8.664,
            "win_loss": -3.823,
            "offense": 16.498,
            "defense": 8.273,
            "state": "UT",
            "mascot": "",
            "backgroundColor": "#333333",
            "textColor": "#FFFFFF",
            "logoURL": "",
            "schoolLogoURL": "",
            "website": "",
            "seasons": 63,
            "hasProgramPage": false,
            "programPageUrl": ""
        },
        {
            "rank": 76,
            "program": "Coalville North Summit (UT)",
            "combined": -13.802,
            "margin": -9.72,
            "win_loss": -4.082,
            "offense": 15.334,
            "defense": 8.043,
            "state": "UT",
            "mascot": "",
            "backgroundColor": "#333333",
            "textColor": "#FFFFFF",
            "logoURL": "",
            "schoolLogoURL": "",
            "website": "",
            "seasons": 59,
            "hasProgramPage": false,
            "programPageUrl": ""
        },
        {
            "rank": 77,
            "program": "Manti (UT)",
            "combined": -13.928,
            "margin": -9.86,
            "win_loss": -4.061,
            "offense": 16.344,
            "defense": 8.635,
            "state": "UT",
            "mascot": "",
            "backgroundColor": "#333333",
            "textColor": "#FFFFFF",
            "logoURL": "",
            "schoolLogoURL": "",
            "website": "",
            "seasons": 56,
            "hasProgramPage": false,
            "programPageUrl": ""
        },
        {
            "rank": 78,
            "program": "Castle Dale Emery County (UT)",
            "combined": -15.219,
            "margin": -10.973,
            "win_loss": -4.189,
            "offense": 16.037,
            "defense": 9.747,
            "state": "UT",
            "mascot": "",
            "backgroundColor": "#333333",
            "textColor": "#FFFFFF",
            "logoURL": "",
            "schoolLogoURL": "",
            "website": "",
            "seasons": 56,
            "hasProgramPage": false,
            "programPageUrl": ""
        },
        {
            "rank": 79,
            "program": "Nephi Juab County (UT)",
            "combined": -15.553,
            "margin": -11.433,
            "win_loss": -4.124,
            "offense": 17.208,
            "defense": 7.732,
            "state": "UT",
            "mascot": "",
            "backgroundColor": "#333333",
            "textColor": "#FFFFFF",
            "logoURL": "",
            "schoolLogoURL": "",
            "website": "",
            "seasons": 60,
            "hasProgramPage": false,
            "programPageUrl": ""
        },
        {
            "rank": 80,
            "program": "Roosevelt Union (UT)",
            "combined": -15.813,
            "margin": -11.59,
            "win_loss": -4.184,
            "offense": 16.707,
            "defense": 9.493,
            "state": "UT",
            "mascot": "",
            "backgroundColor": "#333333",
            "textColor": "#FFFFFF",
            "logoURL": "",
            "schoolLogoURL": "",
            "website": "",
            "seasons": 61,
            "hasProgramPage": false,
            "programPageUrl": ""
        },
        {
            "rank": 81,
            "program": "Enterprise (UT)",
            "combined": -15.863,
            "margin": -13.207,
            "win_loss": -2.701,
            "offense": 7.311,
            "defense": 9.949,
            "state": "UT",
            "mascot": "",
            "backgroundColor": "#333333",
            "textColor": "#FFFFFF",
            "logoURL": "",
            "schoolLogoURL": "",
            "website": "",
            "seasons": 28,
            "hasProgramPage": false,
            "programPageUrl": ""
        },
        {
            "rank": 82,
            "program": "Moab Grand County (UT)",
            "combined": -22.794,
            "margin": -18.295,
            "win_loss": -4.521,
            "offense": 18.44,
            "defense": 2.495,
            "state": "UT",
            "mascot": "",
            "backgroundColor": "#333333",
            "textColor": "#FFFFFF",
            "logoURL": "",
            "schoolLogoURL": "",
            "website": "",
            "seasons": 89,
            "hasProgramPage": false,
            "programPageUrl": ""
        },
        {
            "rank": 83,
            "program": "Monticello (UT)",
            "combined": -28.166,
            "margin": -22.815,
            "win_loss": -5.378,
            "offense": 14.12,
            "defense": 11.824,
            "state": "UT",
            "mascot": "",
            "backgroundColor": "#333333",
            "textColor": "#FFFFFF",
            "logoURL": "",
            "schoolLogoURL": "",
            "website": "",
            "seasons": 56,
            "hasProgramPage": false,
            "programPageUrl": ""
        },
        {
            "rank": 84,
            "program": "Gunnison Valley (UT)",
            "combined": -28.802,
            "margin": -24.191,
            "win_loss": -4.547,
            "offense": 9.398,
            "defense": 13.183,
            "state": "UT",
            "mascot": "",
            "backgroundColor": "#333333",
            "textColor": "#FFFFFF",
            "logoURL": "",
            "schoolLogoURL": "",
            "website": "",
            "seasons": 35,
            "hasProgramPage": false,
            "programPageUrl": ""
        },
        {
            "rank": 85,
            "program": "Monroe South Sevier County (UT)",
            "combined": -29.426,
            "margin": -23.889,
            "win_loss": -5.489,
            "offense": 13.668,
            "defense": 10.87,
            "state": "UT",
            "mascot": "",
            "backgroundColor": "#333333",
            "textColor": "#FFFFFF",
            "logoURL": "",
            "schoolLogoURL": "",
            "website": "",
            "seasons": 55,
            "hasProgramPage": false,
            "programPageUrl": ""
        },
        {
            "rank": 86,
            "program": "Duchesne (UT)",
            "combined": -29.566,
            "margin": -24.032,
            "win_loss": -5.546,
            "offense": 15.49,
            "defense": 9.1,
            "state": "UT",
            "mascot": "",
            "backgroundColor": "#333333",
            "textColor": "#FFFFFF",
            "logoURL": "",
            "schoolLogoURL": "",
            "website": "",
            "seasons": 54,
            "hasProgramPage": false,
            "programPageUrl": ""
        },
        {
            "rank": 87,
            "program": "Milford (UT)",
            "combined": -33.564,
            "margin": -27.621,
            "win_loss": -5.927,
            "offense": 15.331,
            "defense": 11.276,
            "state": "UT",
            "mascot": "",
            "backgroundColor": "#333333",
            "textColor": "#FFFFFF",
            "logoURL": "",
            "schoolLogoURL": "",
            "website": "",
            "seasons": 56,
            "hasProgramPage": false,
            "programPageUrl": ""
        },
        {
            "rank": 88,
            "program": "Salina North Sevier County (UT)",
            "combined": -33.859,
            "margin": -27.965,
            "win_loss": -5.844,
            "offense": 13.943,
            "defense": 10.813,
            "state": "UT",
            "mascot": "",
            "backgroundColor": "#333333",
            "textColor": "#FFFFFF",
            "logoURL": "",
            "schoolLogoURL": "",
            "website": "",
            "seasons": 54,
            "hasProgramPage": false,
            "programPageUrl": ""
        },
        {
            "rank": 89,
            "program": "Parowan (UT)",
            "combined": -39.248,
            "margin": -32.735,
            "win_loss": -6.527,
            "offense": 16.01,
            "defense": 10.245,
            "state": "UT",
            "mascot": "",
            "backgroundColor": "#333333",
            "textColor": "#FFFFFF",
            "logoURL": "",
            "schoolLogoURL": "",
            "website": "",
            "seasons": 58,
            "hasProgramPage": false,
            "programPageUrl": ""
        },
        {
            "rank": 90,
            "program": "Dugway (UT)",
            "combined": -43.706,
            "margin": -35.085,
            "win_loss": -8.584,
            "offense": 23.165,
            "defense": 7.794,
            "state": "UT",
            "mascot": "",
            "backgroundColor": "#333333",
            "textColor": "#FFFFFF",
            "logoURL": "",
            "schoolLogoURL": "",
            "website": "",
            "seasons": 26,
            "hasProgramPage": false,
            "programPageUrl": ""
        },
        {
            "rank": 91,
            "program": "Altamont (UT)",
            "combined": -46.067,
            "margin": -38.826,
            "win_loss": -7.18,
            "offense": 13.557,
            "defense": 10.775,
            "state": "UT",
            "mascot": "",
            "backgroundColor": "#333333",
            "textColor": "#FFFFFF",
            "logoURL": "",
            "schoolLogoURL": "",
            "website": "",
            "seasons": 50,
            "hasProgramPage": false,
            "programPageUrl": ""
        },
        {
            "rank": 92,
            "program": "Montezuma Creek Whitehorse (UT)",
            "combined": -72.914,
            "margin": -63.944,
            "win_loss": -8.923,
            "offense": 7.076,
            "defense": 17.402,
            "state": "UT",
            "mascot": "",
            "backgroundColor": "#333333",
            "textColor": "#FFFFFF",
            "logoURL": "",
            "schoolLogoURL": "",
            "website": "",
            "seasons": 44,
            "hasProgramPage": false,
            "programPageUrl": ""
        },
        {
            "rank": 93,
            "program": "Monument Valley (UT)",
            "combined": -77.927,
            "margin": -68.529,
            "win_loss": -9.326,
            "offense": 9.193,
            "defense": 18.868,
            "state": "UT",
            "mascot": "",
            "backgroundColor": "#333333",
            "textColor": "#FFFFFF",
            "logoURL": "",
            "schoolLogoURL": "",
            "website": "",
            "seasons": 43,
            "hasProgramPage": false,
            "programPageUrl": ""
        }
    ]
}